<?xml version="1.0" encoding="utf-8"?>
<form ID="corPAYEE-0015" sfwActive="True" sfwDescription="Rollover Verification Form" sfwStatus="Review" sfwRemoteObject="busPayeeAccount" sfwType="Correspondence" sfwTemplate="PAYEE-0015.docx" version="4.0" sfwEntity="entPayeeAccount">
  <sfwFieldBookMarks>
    <sfwFieldBookMark ID="PlanId" />
    <sfwFieldBookMark ID="CurrentDate" sfwDataType="String" sfwEntityField="IstrCurrentDate" />
    <sfwFieldBookMark ID="TotalIAPBalance" sfwDataType="Decimal" sfwEntityField="IdecIndividualAccPlanBalance" />
    <sfwFieldBookMark ID="PreTaxAmtReq" sfwDataType="Decimal" sfwEntityField="IdecGrossAmountAfterRollover" />
  </sfwFieldBookMarks>
  <sfwTableBookMarks>
    <sfwTableBookMark ID="tbRolloverVerification" sfwEntityField="lstPayeeAccountRolloverDetail" sfwGridEntity="entPayeeAccountRolloverDetail">
      <sfwColumn sfwColumnHeader="Payable to:" sfwEntityField="IstrPayableTo" />
      <sfwColumn sfwColumnHeader="Amount Required" sfwDataFormat="{0:C}" sfwEntityField="IdecRolloverAmountRequired" />
      <sfwColumn sfwColumnHeader="New amount" sfwDataFormat="{0:C}" sfwEntityField="IstrBlank" />
    </sfwTableBookMark>
  </sfwTableBookMarks>
</form>