<?xml version="1.0" encoding="utf-8"?>
<form ID="wfpPayeeAccountACHMaintenance" sfwActive="True" sfwStatus="Review" sfwType="Maintenance" sfwTitle="Payee Account ACH" version="3.5" sfwEntity="entPrototype">
  <sfwTable ID="Main">
    <sfwRow>
      <sfwColumn>
        <sfwPanel ID="pnltoolbar">
          <sfwTable ID="toolbar">
            <sfwRow>
              <sfwColumn>
                <sfwButton ID="btnSave" sfwMethodName="btnSave_Click" Text="Save" />
                <sfwButton ID="btnCancel" sfwMethodName="btnCancel_Click" Text="Cancel" />
                <sfwButton ID="btnPrev" sfwMethodName="btnPrev_Click" Text="Prev" />
                <sfwButton ID="btnNext" sfwMethodName="btnNext_Click" Text="Next" />
                <sfwButton ID="btnCorrespondence" sfwMethodName="btnCorrespondence_Click" Text="Correspondence" />
              </sfwColumn>
            </sfwRow>
          </sfwTable>
        </sfwPanel>
      </sfwColumn>
    </sfwRow>
    <sfwRow>
      <sfwColumn>
        <sfwPanel ID="pnlSection0" sfwCaption="Payee Information">
          <sfwTable ID="Section0">
            <sfwRow>
              <sfwColumn>
                <sfwLabel ID="lblLabel" Text="Payee Account ID :" sfwIsCaption="True" />
              </sfwColumn>
              <sfwColumn>
                <sfwHyperLink ID="hypHyperLink" Text="M01429990" />
              </sfwColumn>
              <sfwColumn>
                <sfwLabel ID="lblLabel1" Text="Payee Name :" sfwIsCaption="True" />
              </sfwColumn>
              <sfwColumn>
                <sfwHyperLink ID="hypHyperLink1" Text="ELIZABETH ALVAREZ" />
              </sfwColumn>
            </sfwRow>
            <sfwRow>
              <sfwColumn>
                <sfwLabel ID="lblLabel2" Text="Benefit Type :" sfwIsCaption="True" />
              </sfwColumn>
              <sfwColumn>
                <sfwLabel ID="lblLabel3" SkinID="WhiteText" Text="Retirement" sfwIsCaption="True" />
              </sfwColumn>
              <sfwColumn>
                <sfwLabel ID="lblLabel4" Text="Retirement Type :" sfwIsCaption="True" />
              </sfwColumn>
              <sfwColumn>
                <sfwLabel ID="lblLabel5" SkinID="WhiteText" Text="Un-reduced Early Retirement" sfwIsCaption="True" />
              </sfwColumn>
            </sfwRow>
          </sfwTable>
        </sfwPanel>
      </sfwColumn>
    </sfwRow>
    <sfwRow>
      <sfwColumn>
        <sfwPanel ID="pnlNewPage" sfwCaption="ACH Information">
          <sfwTable CssClass="Table" ID="tblNewPage">
            <sfwRow>
              <sfwColumn>
                <sfwLabel ID="lblLabel6" Text="Routing Number :" sfwIsCaption="True" />
              </sfwColumn>
              <sfwColumn>
                <sfwTextBox ID="txtTextBox4" />
                <sfwImageButton ID="btnRetrieve" ImageAlign="AbsMiddle" ImageUrl="~/Image/Lookup.jpg" sfwMethodName="btnRetrieve_Click" sfwRelatedControl="txtTextBox4" />
              </sfwColumn>
              <sfwColumn>
                <sfwLabel ID="lblLabel7" Text="Bank Name :" sfwIsCaption="True" />
              </sfwColumn>
              <sfwColumn>
                <sfwLabel ID="lblLabel15" />
              </sfwColumn>
            </sfwRow>
            <sfwRow>
              <sfwColumn>
                <sfwLabel ID="lblLabel9" Text="Account Number :" sfwIsCaption="True" />
              </sfwColumn>
              <sfwColumn>
                <sfwTextBox ID="txtTextBox1" />
              </sfwColumn>
              <sfwColumn>
                <sfwLabel ID="lblLabel10" Text="Account Type :" sfwIsCaption="True" />
              </sfwColumn>
              <sfwColumn>
                <sfwDropDownList ID="ddlDropDownList" sfwLoadType="Items">
                  <ListItem Value="BLNK" Selected="True" />
                  <ListItem Text="Checking" Value="CHKG" />
                  <ListItem Text="Savings" Value="SAVG" />
                </sfwDropDownList>
              </sfwColumn>
            </sfwRow>
            <sfwRow>
              <sfwColumn>
                <sfwLabel ID="lblLabel12" Text="Primary Account :" Visible="False" sfwIsCaption="True" />
              </sfwColumn>
              <sfwColumn>
                <sfwCheckBox ID="chkCheckBox" sfwDefaultValue="N" Visible="False" />
              </sfwColumn>
              <sfwColumn />
              <sfwColumn />
            </sfwRow>
            <sfwRow>
              <sfwColumn>
                <sfwLabel ID="lblLabel13" Text="Start Date :" sfwIsCaption="True" />
              </sfwColumn>
              <sfwColumn>
                <sfwTextBox ID="txtTextBox2" />
              </sfwColumn>
              <sfwColumn>
                <sfwLabel ID="lblLabel14" Text="End Date :" sfwIsCaption="True" />
              </sfwColumn>
              <sfwColumn>
                <sfwTextBox ID="txtTextBox3" />
              </sfwColumn>
            </sfwRow>
            <sfwRow>
              <sfwColumn>
                <sfwLabel ID="lblLabel11" Text="Percentage :" Visible="False" sfwIsCaption="True" />
              </sfwColumn>
              <sfwColumn>
                <sfwTextBox ID="txtTextBox5" Visible="False" />
              </sfwColumn>
              <sfwColumn>
                <sfwLabel ID="lblLabel16" Text="Flat Amount :" Visible="False" sfwIsCaption="True" />
              </sfwColumn>
              <sfwColumn>
                <sfwTextBox ID="txtTextBox6" Visible="False" />
              </sfwColumn>
            </sfwRow>
            <sfwRow>
              <sfwColumn>
                <sfwLabel ID="lblLabel17" Text="Pre-Note Flag :" sfwIsCaption="True" />
              </sfwColumn>
              <sfwColumn>
                <sfwCheckBox ID="chkCheckBox1" />
              </sfwColumn>
              <sfwColumn>
                <sfwLabel ID="lblLabel18" Text="Pre-Note Completion Date :" sfwIsCaption="True" />
              </sfwColumn>
              <sfwColumn />
            </sfwRow>
            <sfwRow>
              <sfwColumn>
                <sfwButton ID="btnGridViewAddEmptyClick" sfwMethodName="btnGridViewAddEmpty_Click" Text="Add" />
                <sfwButton ID="btnExecutePassSelectedRows" sfwMethodName="btnExecuteBusinessMethodSelectRows_Click" Text="Update" />
                <sfwButton ID="btnGridViewDeleteClick" sfwMethodName="btnGridViewDelete_Click" Text="Delete" />
              </sfwColumn>
              <sfwColumn />
              <sfwColumn />
              <sfwColumn />
            </sfwRow>
            <sfwRow>
              <sfwColumn ColumnSpan="4">
                <sfwGridView AllowPaging="True" AllowSorting="True" AutoGenerateColumns="False" ID="gvACH" sfwSelection="One" sfwEntityField="Collection0">
                  <Columns>
                    <TemplateField HeaderText="Routing Number">
                      <ItemTemplate>
                        <sfwHyperLink sfwEntityField="Property0" />
                      </ItemTemplate>
                    </TemplateField>
                    <TemplateField HeaderText="Bank Name">
                      <ItemTemplate>
                        <sfwLabel sfwEntityField="Property1" />
                      </ItemTemplate>
                    </TemplateField>
                    <TemplateField HeaderText="Account Number">
                      <ItemTemplate>
                        <sfwLabel sfwEntityField="Property2" />
                      </ItemTemplate>
                    </TemplateField>
                    <TemplateField HeaderText="Account Type">
                      <ItemTemplate>
                        <sfwLabel sfwEntityField="Property3" />
                      </ItemTemplate>
                    </TemplateField>
                    <TemplateField HeaderText="Primary Account" Visible="False">
                      <ItemTemplate>
                        <sfwLabel sfwEntityField="Property4" />
                      </ItemTemplate>
                    </TemplateField>
                    <TemplateField HeaderText="Percentage" Visible="False">
                      <ItemTemplate>
                        <sfwLabel sfwEntityField="Property5" />
                      </ItemTemplate>
                    </TemplateField>
                    <TemplateField HeaderText="Flat Amount" Visible="False">
                      <ItemTemplate>
                        <sfwLabel sfwEntityField="Property6" />
                      </ItemTemplate>
                    </TemplateField>
                    <TemplateField HeaderText="Start Date">
                      <ItemTemplate>
                        <sfwLabel sfwEntityField="Property7" />
                      </ItemTemplate>
                    </TemplateField>
                    <TemplateField HeaderText="End Date">
                      <ItemTemplate>
                        <sfwLabel sfwEntityField="Property8" />
                      </ItemTemplate>
                    </TemplateField>
                    <TemplateField HeaderText="Pre-Note Flag">
                      <ItemTemplate>
                        <sfwLabel sfwEntityField="Property9" />
                      </ItemTemplate>
                    </TemplateField>
                    <TemplateField HeaderText="Pre-Note Completion Date">
                      <ItemTemplate>
                        <sfwLabel sfwEntityField="Property10" />
                      </ItemTemplate>
                    </TemplateField>
                  </Columns>
                  <Data>
                    <DataRow>
                      <DataColumn Value="291479673" sfwEntityField="Property0" />
                      <DataColumn Value="Wells Fargo" sfwEntityField="Property1" />
                      <DataColumn Value="2251611 " sfwEntityField="Property2" />
                      <DataColumn Value="Checking" sfwEntityField="Property3" />
                      <DataColumn Value="Yes" sfwEntityField="Property4" />
                      <DataColumn Value="100.00" sfwEntityField="Property5" />
                      <DataColumn sfwEntityField="Property6" />
                      <DataColumn Value="07/01/2012" sfwEntityField="Property7" />
                      <DataColumn sfwEntityField="Property8" />
                      <DataColumn Value="Yes" sfwEntityField="Property9" />
                      <DataColumn Value="06/28/2012" sfwEntityField="Property10" />
                      <DataColumn sfwEntityField="Property11" />
                    </DataRow>
                  </Data>
                </sfwGridView>
              </sfwColumn>
              <sfwColumn />
              <sfwColumn />
              <sfwColumn />
            </sfwRow>
          </sfwTable>
        </sfwPanel>
      </sfwColumn>
    </sfwRow>
    <sfwRow>
      <sfwColumn>
        <sfwPanel ID="pnlAuditInfo" sfwCaption="Audit Information">
          <sfwTable ID="tblAuditInfo">
            <sfwRow>
              <sfwColumn>
                <sfwLabel ID="capCreate" Text="Create : " sfwIsCaption="True" />
              </sfwColumn>
              <sfwColumn>
                <sfwLabel ID="lblCreatedBy" Text="Created By" sfwIsCaption="True" />
              </sfwColumn>
              <sfwColumn>
                <sfwLabel ID="lblCreatedDate" Text="Created Date" sfwIsCaption="True" />
              </sfwColumn>
              <sfwColumn>
                <sfwLabel ID="capModify" Text="Modify : " sfwIsCaption="True" />
              </sfwColumn>
              <sfwColumn>
                <sfwLabel ID="lblModifiedBy" Text="Modified By" sfwIsCaption="True" />
              </sfwColumn>
              <sfwColumn>
                <sfwLabel ID="lblModifiedDate" Text="Modified Date" sfwIsCaption="True" />
              </sfwColumn>
            </sfwRow>
          </sfwTable>
        </sfwPanel>
      </sfwColumn>
    </sfwRow>
  </sfwTable>
</form>