<?xml version="1.0" encoding="utf-8"?>
<form ID="corRETR-0033" sfwActive="True" sfwDescription="Lump Sum Distribution Election" sfwStatus="Valid" sfwRemoteObject="busBenefitCalculationRetirement" sfwType="Correspondence" sfwTemplate="RETR-0033.docx" version="4.0" sfwEntity="entBenefitCalculationRetirement">
  <sfwFieldBookMarks>
    <sfwFieldBookMark ID="PlanId" sfwDataType="Int" sfwEntityField="IintPlanId" />
    <sfwFieldBookMark ID="PartLumpSumBenAmt" sfwDataType="String" sfwEntityField="IstrParticipantLumpSumBenefitAmount" />
    <sfwFieldBookMark ID="LumpSumYear" sfwDataType="Int" sfwEntityField="IintLumpSumYearByAge" />
    <sfwFieldBookMark ID="PartMPIID" sfwDataType="String" sfwEntityField="IstrParticipantMPIID" />
  </sfwFieldBookMarks>
  <sfwQueryBookMarks>
    <sfwQueryBookMark ID="Plan" />
  </sfwQueryBookMarks>
  <sfwQueryForm>
    <sfwTable>
      <sfwRow>
        <sfwColumn>
          <sfwLabel ID="capPlan" Text="Plan" sfwIsCaption="True" />
        </sfwColumn>
        <sfwColumn>
          <sfwDropDownList ID="Plan" sfwQueryID="Plan" sfwLoadType="Items">
            <ListItem Selected="True" />
            <ListItem Text="IAP" Value="1" />
            <ListItem Text="MPIPP/Local" Value="2" />
            <ListItem Text="EE/UVHP" Value="3" />
            <ListItem Text="Local-161 Special Account " Value="4" />
            <ListItem Text="Local -52 Special Account" Value="5" />
          </sfwDropDownList>
        </sfwColumn>
      </sfwRow>
    </sfwTable>
  </sfwQueryForm>
  <sfwAssociatedForms>
    <sfwAssociatedForm ID="wfmBenefitCalculationWithdrawalMaintenance" sfwEntityField="objBenefitCalculationRetirement" />
    <sfwAssociatedForm ID="wfmDisabiltyBenefitCalculationMaintenance" sfwEntityField="objBenefitCalculationRetirement" />
    <sfwAssociatedForm ID="wfmBenefitCalculationPreRetirementDeathMaintenance" sfwEntityField="objBenefitCalculationRetirement" />
  </sfwAssociatedForms>
</form>