<?xml version="1.0" encoding="utf-8"?>
<form ID="corPERO-0010" sfwActive="True" sfwDescription="IAP Annual Summary" sfwStatus="Review" sfwRemoteObject="busIAPAllocationDetailPersonOverview" sfwType="Correspondence" sfwTemplate="PERO-0010.docx" version="4.0" sfwEntity="entIAPAllocationDetailPersonOverview">
  <sfwFieldBookMarks>
    <sfwFieldBookMark ID="PlanId" sfwObjectID="busIAPAllocationDetailPersonOverview" />
    <sfwFieldBookMark ID="Name" sfwEntityField="IstrFullName" />
    <sfwFieldBookMark ID="MPID" sfwEntityField="MpiPersonId" />
    <sfwFieldBookMark ID="DOB" sfwEntityField="IdtDateofBirth" />
    <sfwFieldBookMark ID="totalCummulativeBal" sfwDataFormat="{0:C}" sfwDataType="Decimal" sfwEntityField="IdecIAPAccountBalance" />
  </sfwFieldBookMarks>
  <sfwTableBookMarks>
    <sfwTableBookMark ID="IAP" sfwEntityField="lstIAPAllocationDetailPersonOverview" sfwGridEntity="entIapAllocationDetailCalculation">
      <sfwColumn sfwColumnHeader="Computation Year" sfwEntityField="ComputationalYear" />
      <sfwColumn sfwColumnHeader="Credited Hours" sfwDataType="Decimal" sfwEntityField="Ytdhours" />
      <sfwColumn sfwColumnHeader="Annual Benefit" sfwDataFormat="{0:C}" sfwEntityField="Total" />
      <sfwColumn sfwColumnHeader="Cumulative Balance" sfwDataFormat="{0:C}" sfwEntityField="IapAccountBalance" />
    </sfwTableBookMark>
  </sfwTableBookMarks>
</form>